anyblok_attachment_jinja/__init__.py
anyblok_attachment_jinja/release.py
anyblok_attachment_jinja/bloks/__init__.py
anyblok_attachment_jinja/bloks/jinja/CODE.rst
anyblok_attachment_jinja/bloks/jinja/README.rst
anyblok_attachment_jinja/bloks/jinja/__init__.py
anyblok_attachment_jinja/bloks/jinja/exceptions.py
anyblok_attachment_jinja/bloks/jinja/parser.py
anyblok_attachment_jinja/bloks/jinja/template.py
anyblok_attachment_jinja/bloks/jinja/tests/__init__.py
anyblok_attachment_jinja/bloks/jinja/tests/test_template.py
anyblok_attachment_jinja-1.0.0.dist-info/LICENSE.txt
anyblok_attachment_jinja-1.0.0.dist-info/METADATA
anyblok_attachment_jinja-1.0.0.dist-info/RECORD
anyblok_attachment_jinja-1.0.0.dist-info/WHEEL
anyblok_attachment_jinja-1.0.0.dist-info/entry_points.txt
anyblok_attachment_jinja-1.0.0.dist-info/top_level.txt
