Metadata-Version: 2.1
Name: anyblok-attachment-jinja
Version: 1.0.0
Summary: Jinja templating for AnyBlok attachment
Home-page: http://docs.anyblok-attachment-jinja.anyblok.org/1.0.0
Author: jssuzanne
Author-email: jssuzanne@anybox.fr
License: UNKNOWN
Keywords: attachment
Platform: UNKNOWN
Classifier: Development Status :: 5 - Production/Stable
Classifier: Intended Audience :: Developers
Classifier: Natural Language :: English
Classifier: Programming Language :: Python :: 3
Classifier: Programming Language :: Python :: 3.4
Classifier: Programming Language :: Python :: 3.5
Classifier: Programming Language :: Python :: 3.6
Classifier: Programming Language :: Python :: 3.7
Requires-Dist: anyblok
Requires-Dist: anyblok-attachment
Requires-Dist: jinja2
